HMGeneric/__init__.py
HMGeneric/array.py
HMGeneric/ethernet.py
HMGeneric/file.py
HMGeneric/internetProtocol.py
HMGeneric/menu.py
HMGeneric/module.py
HMGeneric/parse.py
HMGeneric/registry.py
HMGeneric/service.py
HMGeneric/terminal.py
HMGeneric/wmi.py
HMGeneric-1.0.13.dist-info/LICENSE.txt
HMGeneric-1.0.13.dist-info/METADATA
HMGeneric-1.0.13.dist-info/WHEEL
HMGeneric-1.0.13.dist-info/top_level.txt
HMGeneric-1.0.13.dist-info/RECORD
